leftcorner/__init__.py
leftcorner/cfg.py
leftcorner/misc.py
leftcorner/semiring.py
leftcorner-1.0.1.dist-info/METADATA
leftcorner-1.0.1.dist-info/WHEEL
leftcorner-1.0.1.dist-info/top_level.txt
leftcorner-1.0.1.dist-info/RECORD
